{
  "keyword": "e-commerce prediction",
  "timestamp": "2026-03-30T17:28:02.612085",
  "count": 20,
  "papers": [
    {
      "title": "Customer data prediction and analysis in e-commerce using machine learning",
      "authors": "MA Al Rahib, N Saha, R Mia, A Sattar",
      "year": 2024,
      "venue": "beei2.org",
      "abstract": "… , but in this research, we predict and analyze product on-time delivery in e-commerce [15]. … and some are on e-commerce. But in this research, we predict and analyze customer churn …",
      "url": "http://beei2.org/index.php/EEI/article/view/6420",
      "citations": 21,
      "source": "SerpAPI",
      "relevance_score": 50,
      "summary": "",
      "chinese_explanation": "",
      "applications": "",
      "suggestions": "",
      "relevance_stars": "★★★☆☆",
      "relevance_reason": "",
      "score": 45,
      "score_details": "引用21(较少); 非顶会; 2年内; 完整度15/15; 部分相关",
      "level": "D",
      "level_desc": "参考"
    },
    {
      "title": "Machine learning for enabling strategic insights to future-proof E-Commerce",
      "authors": "CS Kodete, V Pasupuleti, B Thuraka",
      "year": 2024,
      "venue": "ieeexplore.ieee.org",
      "abstract": "… secondary data to predict market value, … predictions and actionable insights for e-commerce practitioners. It demonstrates the potential of machine learning to transform ecommerce …",
      "url": "https://ieeexplore.ieee.org/abstract/document/10722255/",
      "citations": 18,
      "source": "SerpAPI",
      "relevance_score": 50,
      "summary": "",
      "chinese_explanation": "",
      "applications": "",
      "suggestions": "",
      "relevance_stars": "★★★☆☆",
      "relevance_reason": "",
      "score": 45,
      "score_details": "引用18(较少); 非顶会; 2年内; 完整度15/15; 部分相关",
      "level": "D",
      "level_desc": "参考"
    },
    {
      "title": "Deep Learning for e-Commerce: Recent Developments in Prediction, Personalization and Decision Intelligence",
      "authors": "G Kostopoulos, A Stefani, V Vasiliadis, S Kotsiantis",
      "year": 2026,
      "venue": "mdpi.com",
      "abstract": "… -making in the e-commerce chain. In this evolving landscape of research on DL for e-commerce intelligence, we can conceptually identify three closely interrelated aspects: prediction, …",
      "url": "https://www.mdpi.com/2076-3417/16/5/2263",
      "citations": 0,
      "source": "SerpAPI",
      "relevance_score": 50,
      "summary": "",
      "chinese_explanation": "",
      "applications": "",
      "suggestions": "",
      "relevance_stars": "★★★☆☆",
      "relevance_reason": "",
      "score": 45,
      "score_details": "引用0(新/少); 非顶会; 当年新文; 完整度15/15; 部分相关",
      "level": "D",
      "level_desc": "参考"
    },
    {
      "title": "Research on multimodal prediction of e-commerce customer satisfaction driven by big data",
      "authors": "X Zhang, C Guo",
      "year": 2024,
      "venue": "mdpi.com",
      "abstract": "… [33] explored e-commerce product classification using a … neural network model for predicting e-commerce product demand. … to predict product return rates in live-streaming e-commerce. …",
      "url": "https://www.mdpi.com/2076-3417/14/18/8181",
      "citations": 27,
      "source": "SerpAPI",
      "relevance_score": 50,
      "summary": "",
      "chinese_explanation": "",
      "applications": "",
      "suggestions": "",
      "relevance_stars": "★★★☆☆",
      "relevance_reason": "",
      "score": 45,
      "score_details": "引用27(较少); 非顶会; 2年内; 完整度15/15; 部分相关",
      "level": "D",
      "level_desc": "参考"
    },
    {
      "title": "Enhancing e-commerce strategies: A deep learning framework for customer behavior prediction",
      "authors": "YD Al-Otaibi",
      "year": 2024,
      "venue": "etasr.com",
      "abstract": "… ecommerce as it uses the past purchasing behavior of customer-automated processes. Nevertheless, predicting … This predictive model offers valuable lessons for e-commerce because …",
      "url": "https://www.etasr.com/index.php/ETASR/article/view/7945",
      "citations": 17,
      "source": "SerpAPI",
      "relevance_score": 50,
      "summary": "",
      "chinese_explanation": "",
      "applications": "",
      "suggestions": "",
      "relevance_stars": "★★★☆☆",
      "relevance_reason": "",
      "score": 45,
      "score_details": "引用17(较少); 非顶会; 2年内; 完整度15/15; 部分相关",
      "level": "D",
      "level_desc": "参考"
    },
    {
      "title": "Predictions for Consumer Behaviour of E-Commerce Sales Data 2023-2024 Based on the LightGBM Model",
      "authors": "J Du",
      "year": 2025,
      "venue": "scitepress.org",
      "abstract": "… on e-commerce platforms. This provides valuable insights for e-commerce businesses, … using a relatively simple but effective model to predict the likelihood of customer ratings, it …",
      "url": "https://www.scitepress.org/Papers/2024/132074/132074.pdf",
      "citations": 1,
      "source": "SerpAPI",
      "relevance_score": 50,
      "summary": "",
      "chinese_explanation": "",
      "applications": "",
      "suggestions": "",
      "relevance_stars": "★★★☆☆",
      "relevance_reason": "",
      "score": 43,
      "score_details": "引用1(新/少); 非顶会; 1年内; 完整度15/15; 部分相关",
      "level": "D",
      "level_desc": "参考"
    },
    {
      "title": "Decoding E-Commerce Fluctuations: A Machine Learning Analysis Of Influential Variables During Us Covid-19 (2010-2024)",
      "authors": "K Ungar",
      "year": 2025,
      "venue": "papers.ssrn.com",
      "abstract": "… These findings provide valuable guidance for practitioners on leveraging economic indicators to predict and enhance e-commerce trends. The study's model analyzes the influence of …",
      "url": "https://papers.ssrn.com/sol3/papers.cfm?abstract_id=5151887",
      "citations": 0,
      "source": "SerpAPI",
      "relevance_score": 50,
      "summary": "",
      "chinese_explanation": "",
      "applications": "",
      "suggestions": "",
      "relevance_stars": "★★★☆☆",
      "relevance_reason": "",
      "score": 43,
      "score_details": "引用0(新/少); 非顶会; 1年内; 完整度15/15; 部分相关",
      "level": "D",
      "level_desc": "参考"
    },
    {
      "title": "USING BIG DATA AND AI TO PREDICT CONSUMER BEHAVIOUR IN E-COMMERCE",
      "authors": "R Shynkarenko",
      "year": 2025,
      "venue": "nzlubp.org.ua",
      "abstract": "… analytical techniques in predicting consumer behavior within e-commerce. The increasing … of the efficiency of implemented solutions based on real-world applications in e-commerce. …",
      "url": "https://nzlubp.org.ua/index.php/journal/article/view/1549",
      "citations": 1,
      "source": "SerpAPI",
      "relevance_score": 50,
      "summary": "",
      "chinese_explanation": "",
      "applications": "",
      "suggestions": "",
      "relevance_stars": "★★★☆☆",
      "relevance_reason": "",
      "score": 43,
      "score_details": "引用1(新/少); 非顶会; 1年内; 完整度15/15; 部分相关",
      "level": "D",
      "level_desc": "参考"
    },
    {
      "title": "Enhancing e-commerce dynamics through deep learning-based customer demand prediction",
      "authors": "MM Ahmmed, MM Rahman, M Mahmud",
      "year": 2025,
      "venue": "Elsevier",
      "abstract": "… of deep learning in e-commerce, offering businesses crucial … a robust framework for e-commerce businesses aiming for … and business strategy in the dynamic world of e-commerce. …",
      "url": "https://www.sciencedirect.com/science/article/pii/S235214652500105X",
      "citations": 6,
      "source": "SerpAPI",
      "relevance_score": 50,
      "summary": "",
      "chinese_explanation": "",
      "applications": "",
      "suggestions": "",
      "relevance_stars": "★★★☆☆",
      "relevance_reason": "",
      "score": 43,
      "score_details": "引用6(新/少); 非顶会; 1年内; 完整度15/15; 部分相关",
      "level": "D",
      "level_desc": "参考"
    },
    {
      "title": "Integration of machine learning in e-commerce: A systematic literature review on consumer behavior prediction and product recommendation",
      "authors": "AR Syamsuri, R Arohman",
      "year": 2025,
      "venue": "journal.midpublisher.com",
      "abstract": "… ) in ecommerce, focusing on consumer behavior prediction … approaches by function (prediction vs. recommendation) and … performance across different e-commerce contexts; and (3) …",
      "url": "https://journal.midpublisher.com/index.php/ssij/article/view/203",
      "citations": 0,
      "source": "SerpAPI",
      "relevance_score": 50,
      "summary": "",
      "chinese_explanation": "",
      "applications": "",
      "suggestions": "",
      "relevance_stars": "★★★☆☆",
      "relevance_reason": "",
      "score": 43,
      "score_details": "引用0(新/少); 非顶会; 1年内; 完整度15/15; 部分相关",
      "level": "D",
      "level_desc": "参考"
    },
    {
      "title": "Cluster-based prediction for product sales of E-commerce after COVID-19 pandemic",
      "authors": "Z Lv, H Kang, Z Gao, X Zhuang, J Tang, Z Wang",
      "year": 2025,
      "venue": "Springer",
      "abstract": "… emergency, predicting product sales in e-commerce can help … (called DKCLA) to predict E-commerce sales after the … -based prediction model to predict the E-commerce product …",
      "url": "https://link.springer.com/article/10.1007/s13042-024-02503-x",
      "citations": 1,
      "source": "SerpAPI",
      "relevance_score": 50,
      "summary": "",
      "chinese_explanation": "",
      "applications": "",
      "suggestions": "",
      "relevance_stars": "★★★☆☆",
      "relevance_reason": "",
      "score": 43,
      "score_details": "引用1(新/少); 非顶会; 1年内; 完整度15/15; 部分相关",
      "level": "D",
      "level_desc": "参考"
    },
    {
      "title": "Research on cross-border e-commerce supply chain prediction and optimization model based on convolutional neural network algorithm",
      "authors": "Y Zhao, B Gong, B Huang",
      "year": 2025,
      "venue": "jstage.jst.go.jp",
      "abstract": "… prediction model that effectively captures both the seasonal and nonlinear characteristics of cross-border e-commerce … for cross-border e-commerce enterprises in reducing costs and …",
      "url": "https://www.jstage.jst.go.jp/article/jaciii/29/1/29_215/_article/-char/ja/",
      "citations": 5,
      "source": "SerpAPI",
      "relevance_score": 50,
      "summary": "",
      "chinese_explanation": "",
      "applications": "",
      "suggestions": "",
      "relevance_stars": "★★★☆☆",
      "relevance_reason": "",
      "score": 43,
      "score_details": "引用5(新/少); 非顶会; 1年内; 完整度15/15; 部分相关",
      "level": "D",
      "level_desc": "参考"
    },
    {
      "title": "E-commerce in a digital future",
      "authors": "V Domashenko",
      "year": 2024,
      "venue": "essuir.sumdu.edu.ua",
      "abstract": "… Chapter 3 deals prediction of the future for e-commerce; deals emerging technologies and their potential impact; deals strategies for businesses to stay ahead in the digital marketplace …",
      "url": "https://essuir.sumdu.edu.ua/items/55587e23-37cc-4d90-8fbb-816314c949b7",
      "citations": 1,
      "source": "SerpAPI",
      "relevance_score": 50,
      "summary": "",
      "chinese_explanation": "",
      "applications": "",
      "suggestions": "",
      "relevance_stars": "★★★☆☆",
      "relevance_reason": "",
      "score": 40,
      "score_details": "引用1(新/少); 非顶会; 2年内; 完整度15/15; 部分相关",
      "level": "D",
      "level_desc": "参考"
    },
    {
      "title": "Predicting E-Commerce Sales with Three Machine Learning Models",
      "authors": "X Li",
      "year": 2024,
      "venue": "books.google.com",
      "abstract": "… In this paper, sales data on the e-commerce platform of an online retail store registered in … In summary, e-commerce sales prediction involves many ML models, and the prediction …",
      "url": "https://books.google.com/books?hl=en&lr=&id=vfEoEQAAQBAJ&oi=fnd&pg=PA445&dq=e-commerce+prediction+after:2021+before:2026&ots=lJE-KJFhH2&sig=uxcb7v-LImUu387yjS0IfA7QFnc",
      "citations": 2,
      "source": "SerpAPI",
      "relevance_score": 50,
      "summary": "",
      "chinese_explanation": "",
      "applications": "",
      "suggestions": "",
      "relevance_stars": "★★★☆☆",
      "relevance_reason": "",
      "score": 40,
      "score_details": "引用2(新/少); 非顶会; 2年内; 完整度15/15; 部分相关",
      "level": "D",
      "level_desc": "参考"
    },
    {
      "title": "Analysing e-commerce transformation: a study on AI-based consumer behaviour prediction",
      "authors": "I Plazibat, I Kekez",
      "year": 2024,
      "venue": "researchgate.net",
      "abstract": "… consumer behaviour in e-commerce? RQ2: … e-commerce? RQ3: What are the reported artificial intelligence methods and fields regarding consumer behaviour analysis in e-commerce…",
      "url": "https://www.researchgate.net/profile/Elsa-Zela/publication/385346415_CIET_2024_Conference_Proceedings_2/links/6720fa855852dd723c9c94e9/CIET-2024-Conference-Proceedings-2.pdf#page=115",
      "citations": 3,
      "source": "SerpAPI",
      "relevance_score": 50,
      "summary": "",
      "chinese_explanation": "",
      "applications": "",
      "suggestions": "",
      "relevance_stars": "★★★☆☆",
      "relevance_reason": "",
      "score": 40,
      "score_details": "引用3(新/少); 非顶会; 2年内; 完整度15/15; 部分相关",
      "level": "D",
      "level_desc": "参考"
    },
    {
      "title": "Form Uncertainty to Sustainable Decision-Making: A Novel MIDAS–AM–DeepAR-Based Prediction Model for E-Commerce Industry Development",
      "authors": "F Huang, M Lin, SI Khattak",
      "year": 2024,
      "venue": "mdpi.com",
      "abstract": "… This paper proposes a new integrative prediction model to track the sustainable development of e-commerce. Using US e-commerce data, this study explores the prediction accuracy of …",
      "url": "https://www.mdpi.com/2071-1050/16/14/6029",
      "citations": 4,
      "source": "SerpAPI",
      "relevance_score": 50,
      "summary": "",
      "chinese_explanation": "",
      "applications": "",
      "suggestions": "",
      "relevance_stars": "★★★☆☆",
      "relevance_reason": "",
      "score": 40,
      "score_details": "引用4(新/少); 非顶会; 2年内; 完整度15/15; 部分相关",
      "level": "D",
      "level_desc": "参考"
    },
    {
      "title": "Efficient customer behaviour prediction in I ndian metropolitan cities for E‐commerce applications",
      "authors": "BS Suresh, M Suresh",
      "year": 2024,
      "venue": "Wiley Online Library",
      "abstract": "… prediction in Indian metropolitan cities for E-commerce … enhancing several aspects of e-commerce operations, including … ) model for future customer behaviour prediction. The efficacy of …",
      "url": "https://onlinelibrary.wiley.com/doi/abs/10.1111/exsy.13604",
      "citations": 5,
      "source": "SerpAPI",
      "relevance_score": 50,
      "summary": "",
      "chinese_explanation": "",
      "applications": "",
      "suggestions": "",
      "relevance_stars": "★★★☆☆",
      "relevance_reason": "",
      "score": 40,
      "score_details": "引用5(新/少); 非顶会; 2年内; 完整度15/15; 部分相关",
      "level": "D",
      "level_desc": "参考"
    },
    {
      "title": "A prediction model for benefitting e-commerce through usage of regional data: A new framework",
      "authors": "S Singhal, P Tanwar",
      "year": 2021,
      "venue": "academia.edu",
      "abstract": "… E-commerce industries are highly popular and they … e-commerce industry. Kalambe [7], has discussed about challenges faced by urban and rural areas in India in context to ecommerce. …",
      "url": "https://www.academia.edu/download/77651374/13251.pdf",
      "citations": 10,
      "source": "SerpAPI",
      "relevance_score": 50,
      "summary": "",
      "chinese_explanation": "",
      "applications": "",
      "suggestions": "",
      "relevance_stars": "★★★☆☆",
      "relevance_reason": "",
      "score": 38,
      "score_details": "引用10(较少); 非顶会; 5年前; 完整度15/15; 部分相关",
      "level": "D",
      "level_desc": "参考"
    },
    {
      "title": "Data analysis and prediction modeling based on deep learning in e‐commerce",
      "authors": "L Feng",
      "year": 2022,
      "venue": "Wiley Online Library",
      "abstract": "… Since the purpose of this paper is to predict the user's purchase behavior on e-commerce platforms to achieve accurate product recommendation, this paper focuses on the distribution …",
      "url": "https://onlinelibrary.wiley.com/doi/abs/10.1155/2022/1041741",
      "citations": 18,
      "source": "SerpAPI",
      "relevance_score": 50,
      "summary": "",
      "chinese_explanation": "",
      "applications": "",
      "suggestions": "",
      "relevance_stars": "★★★☆☆",
      "relevance_reason": "",
      "score": 38,
      "score_details": "引用18(较少); 非顶会; 4年前; 完整度15/15; 部分相关",
      "level": "D",
      "level_desc": "参考"
    },
    {
      "title": "Prediction of the future trend of e-commerce",
      "authors": "F Engström, D Nilsson Rojas",
      "year": 2021,
      "venue": "diva-portal.org",
      "abstract": "… , to predict future trends of electronic commerce in Sweden. More precise, to predict the … Companies can thereby possibly use the models to predict the behaviour of certain smaller …",
      "url": "https://www.diva-portal.org/smash/record.jsf?pid=diva2:1594363",
      "citations": 4,
      "source": "SerpAPI",
      "relevance_score": 50,
      "summary": "",
      "chinese_explanation": "",
      "applications": "",
      "suggestions": "",
      "relevance_stars": "★★★☆☆",
      "relevance_reason": "",
      "score": 33,
      "score_details": "引用4(新/少); 非顶会; 5年前; 完整度15/15; 部分相关",
      "level": "D",
      "level_desc": "参考"
    }
  ]
}