{
  "keyword": "e-commerce",
  "timestamp": "2026-03-30T17:26:56.474871",
  "count": 8,
  "papers": [
    {
      "title": "E-commerce",
      "authors": "KC Laudon, CG Traver",
      "year": 2014,
      "venue": "ir.harambeeuniversity.edu.et",
      "abstract": "… -date and comprehensive overview of e-commerce today. The e-commerce concepts you learn in this book will make you valuable to potential employers. The e-commerce job market is …",
      "url": "http://ir.harambeeuniversity.edu.et/bitstream/handle/123456789/1618/E-Commerce%20%2810th%20Edition%29%20%28%20PDFDrive%20%29.pdf?sequence=1&isAllowed=y",
      "citations": 3394,
      "source": "SerpAPI",
      "relevance_score": 50,
      "summary": "",
      "chinese_explanation": "",
      "applications": "",
      "suggestions": "",
      "relevance_stars": "★★★☆☆",
      "relevance_reason": "",
      "score": 55,
      "score_details": "引用3394(顶级); 非顶会; 12年前(较旧); 完整度15/15; 部分相关",
      "level": "C",
      "level_desc": "一般"
    },
    {
      "title": "Methods and Applications of Quick Commerce (Q-Commerce)",
      "authors": "S. Kavitha, K. Santhanalaxmi",
      "year": 2025,
      "venue": "Methods and Applications of Quick Commerce (Q-Commerce)",
      "abstract": "<jats:p>A completely new business model that emerged during the COVID-19 pandemic is quick commerce. During COVID-19, lockdowns and social alienation forced many to purchase goods online, particularly groceries and perishables. With prominent platforms offering immediate delivery, it has become known as a major trend in the rapidly evolving Indian retail industry, raising the standard for ease. The long-term viability of this quick service in India's D2C market is still up in the air, though. Quick commerce has grown as a result of rising demand and a desire for speedy delivery. The emphasis on quick deliveries where products and services are delivered within 10 to 30 minutes of receiving an order has revolutionized retail establishments in India. It uses a dark store for operating its Kirana store. Quick commerce is more helpful when it comes to delivery speed than traditional retail stores, which are open around-the-clock.</jats:p>",
      "url": "https://doi.org/10.4018/979-8-3373-1712-0.ch010",
      "citations": 1,
      "source": "CrossRef",
      "relevance_score": 50,
      "summary": "",
      "chinese_explanation": "",
      "applications": "",
      "suggestions": "",
      "relevance_stars": "★★★☆☆",
      "relevance_reason": "",
      "score": 43,
      "score_details": "引用1(新/少); 非顶会; 1年内; 完整度15/15; 部分相关",
      "level": "D",
      "level_desc": "参考"
    },
    {
      "title": "Panorama de l'aide pour le commerce 2022",
      "authors": ", ",
      "year": 2024,
      "venue": "Panorama de l'aide pour le commerce",
      "abstract": "",
      "url": "https://doi.org/10.1787/a3412026-fr",
      "citations": 0,
      "source": "CrossRef",
      "relevance_score": 50,
      "summary": "",
      "chinese_explanation": "",
      "applications": "",
      "suggestions": "",
      "relevance_stars": "★★★☆☆",
      "relevance_reason": "",
      "score": 36,
      "score_details": "引用0(新/少); 非顶会; 2年内; 完整度11/15; 部分相关",
      "level": "D",
      "level_desc": "参考"
    },
    {
      "title": "Introduction: Roman Law and Maritime Commerce",
      "authors": "Peter Candy, Emilia Mataix Ferrándiz",
      "year": 2022,
      "venue": "Roman Law and Maritime Commerce",
      "abstract": "<p>This chapter introduces readers to the two of the major contributions to the history of Roman commercial law (Paul Huvelin and Jean Rougé). The chapter examines some of the past approaches to the study of Roman commercial law and examines the potential and pitfalls of adopting an interdisciplinary approach.</p>",
      "url": "https://doi.org/10.3366/edinburgh/9781474478144.003.0001",
      "citations": 0,
      "source": "CrossRef",
      "relevance_score": 50,
      "summary": "",
      "chinese_explanation": "",
      "applications": "",
      "suggestions": "",
      "relevance_stars": "★★★☆☆",
      "relevance_reason": "",
      "score": 33,
      "score_details": "引用0(新/少); 非顶会; 4年前; 完整度15/15; 部分相关",
      "level": "D",
      "level_desc": "参考"
    },
    {
      "title": "Connectivité numérique, commerce électronique et commerce durable",
      "authors": "",
      "year": 2023,
      "venue": "Examen global 2022 de l'Aide pour le commerce",
      "abstract": "",
      "url": "https://doi.org/10.30875/9789287073327c006",
      "citations": 0,
      "source": "CrossRef",
      "relevance_score": 50,
      "summary": "",
      "chinese_explanation": "",
      "applications": "",
      "suggestions": "",
      "relevance_stars": "★★★☆☆",
      "relevance_reason": "",
      "score": 30,
      "score_details": "引用0(新/少); 非顶会; 3年内; 完整度8/15; 部分相关",
      "level": "D",
      "level_desc": "参考"
    },
    {
      "title": "La décarbonation du commerce international",
      "authors": "",
      "year": 2023,
      "venue": "Rapport sur le Commerce Mondial",
      "abstract": "",
      "url": "https://doi.org/10.30875/9789287053992c011",
      "citations": 0,
      "source": "CrossRef",
      "relevance_score": 50,
      "summary": "",
      "chinese_explanation": "",
      "applications": "",
      "suggestions": "",
      "relevance_stars": "★★★☆☆",
      "relevance_reason": "",
      "score": 30,
      "score_details": "引用0(新/少); 非顶会; 3年内; 完整度8/15; 部分相关",
      "level": "D",
      "level_desc": "参考"
    },
    {
      "title": "La tarification du carbone et le commerce international",
      "authors": "",
      "year": 2023,
      "venue": "Rapport sur le Commerce Mondial",
      "abstract": "",
      "url": "https://doi.org/10.30875/9789287053992c010",
      "citations": 0,
      "source": "CrossRef",
      "relevance_score": 50,
      "summary": "",
      "chinese_explanation": "",
      "applications": "",
      "suggestions": "",
      "relevance_stars": "★★★☆☆",
      "relevance_reason": "",
      "score": 30,
      "score_details": "引用0(新/少); 非顶会; 3年内; 完整度8/15; 部分相关",
      "level": "D",
      "level_desc": "参考"
    },
    {
      "title": "Examen statistique du commerce mondial 2021",
      "authors": "",
      "year": 2021,
      "venue": "Examen Statistique du Commerce Mondial",
      "abstract": "",
      "url": "https://doi.org/10.30875/865b2c3f-fr",
      "citations": 0,
      "source": "CrossRef",
      "relevance_score": 50,
      "summary": "",
      "chinese_explanation": "",
      "applications": "",
      "suggestions": "",
      "relevance_stars": "★★★☆☆",
      "relevance_reason": "",
      "score": 26,
      "score_details": "引用0(新/少); 非顶会; 5年前; 完整度8/15; 部分相关",
      "level": "D",
      "level_desc": "参考"
    }
  ]
}